{
  "@context": {
    "ldp": "http://www.w3.org/ns/ldp#",
    "schema": "http://schema.org/",
    "fedora": "http://fedora.info/definitions/v4/repository#",
    "webac": "http://fedora.info/definitions/v4/webac#",
    "acl": "http://www.w3.org/ns/auth/acl#",
    "ucdlib": "http://digital.ucdavis.edu/schema#",
    "ebucore": "http://www.ebu.ch/metadata/ontologies/ebucore/ebucore#"
  },
  "@id": "",
  "@type": [
    "schema:CreativeWork",
    "schema:Photograph",
    "http://fedora.info/definitions/v4/repository#ArchivalGroup"
  ],
  "schema:about": [
    {
      "@id": "http://id.worldcat.org/fast/0908690"
    },
    {
      "@id": "http://id.worldcat.org/fast/1210276"
    }
  ],
  "schema:description": "Gurdev Khush poses for the camera with two boys in Rurkee, India. From the personal records of Gurdev Khush.",
  "schema:identifier": [
    "ark:/87293/d3759r"
  ],
  "schema:license": {
    "@id": "http://rightsstatements.org/vocab/InC-NC/1.0/"
  },
  "schema:name": "Gurdev Khush with Two Boys",
  "schema:publisher": "UC Davis Library, Archives and Special Collections",
  "schema:temporal": "c. 1950"
}
